{
  "children": [
    {
      "children": [
        {
          "children": [
            {
              "children": [
                {
                  "properties": {
                    "alignSelf": "full",
                    "borderRadius": 5,
                    "src": "https://yelp-photos-devc2.yelpcorp.com/bphoto/YdJZZFPpF0KRyuvM0VctMQ/258s.jpg"
                  },
                  "type": "IMAGE"
                },
                {
                  "properties": {
                    "fontSize": 12,
                    "spacing": 0,
                    "text": {
                      "content": [
                        {
                          "marks": [
                            {
                              "type": "strong"
                            }
                          ],
                          "text": "California Roll",
                          "type": "text"
                        }
                      ],
                      "type": "doc"
                    }
                  },
                  "type": "TEXT"
                },
                {
                  "properties": {
                    "fontSize": 12,
                    "spacing": 0,
                    "text": {
                      "content": [
                        {
                          "text": "15 reviews • 8 photos",
                          "type": "text"
                        }
                      ],
                      "type": "paragraph"
                    }
                  },
                  "type": "TEXT"
                }
              ],
              "properties": {
                "spacing": 0.5
              },
              "type": "STACK_LAYOUT"
            }
          ],
          "properties": {
            "spacing": 0.85
          },
          "type": "CLUSTER_LAYOUT"
        }
      ],
      "properties": {
        "span": 3
      },
      "type": "COLUMN"
    },
    {
      "children": [
        {
          "children": [
            {
              "children": [
                {
                  "properties": {
                    "alignSelf": "full",
                    "borderRadius": 5,
                    "src": "https://yelp-photos-devc2.yelpcorp.com/bphoto/gwvLF-RkP7U4otpi4LKZ_w/258s.jpg"
                  },
                  "type": "IMAGE"
                },
                {
                  "properties": {
                    "fontSize": 12,
                    "spacing": 0,
                    "text": {
                      "content": [
                        {
                          "marks": [
                            {
                              "type": "strong"
                            }
                          ],
                          "text": "Shrimp Tempura",
                          "type": "text"
                        }
                      ],
                      "type": "doc"
                    }
                  },
                  "type": "TEXT"
                },
                {
                  "properties": {
                    "fontSize": 12,
                    "spacing": 0,
                    "text": {
                      "content": [
                        {
                          "text": "14 reviews • 6 photos",
                          "type": "text"
                        }
                      ],
                      "type": "paragraph"
                    }
                  },
                  "type": "TEXT"
                }
              ],
              "properties": {
                "spacing": 0.5
              },
              "type": "STACK_LAYOUT"
            }
          ],
          "properties": {
            "spacing": 0.85
          },
          "type": "CLUSTER_LAYOUT"
        }
      ],
      "properties": {
        "span": 3
      },
      "type": "COLUMN"
    },
    {
      "children": [
        {
          "children": [
            {
              "children": [
                {
                  "properties": {
                    "alignSelf": "full",
                    "borderRadius": 5,
                    "src": "https://yelp-photos-devc4.yelpcorp.com/bphoto/-dfvY_Iw7gqwZrplqrgEfQ/258s.jpg"
                  },
                  "type": "IMAGE"
                },
                {
                  "properties": {
                    "fontSize": 12,
                    "spacing": 0,
                    "text": {
                      "content": [
                        {
                          "marks": [
                            {
                              "type": "strong"
                            }
                          ],
                          "text": "Spicy Tuna Roll",
                          "type": "text"
                        }
                      ],
                      "type": "doc"
                    }
                  },
                  "type": "TEXT"
                },
                {
                  "properties": {
                    "fontSize": 12,
                    "spacing": 0,
                    "text": {
                      "content": [
                        {
                          "text": "14 reviews • 5 photos",
                          "type": "text"
                        }
                      ],
                      "type": "paragraph"
                    }
                  },
                  "type": "TEXT"
                }
              ],
              "properties": {
                "spacing": 0.5
              },
              "type": "STACK_LAYOUT"
            }
          ],
          "properties": {
            "spacing": 0.85
          },
          "type": "CLUSTER_LAYOUT"
        }
      ],
      "properties": {
        "span": 3
      },
      "type": "COLUMN"
    },
    {
      "children": [
        {
          "children": [
            {
              "children": [
                {
                  "properties": {
                    "alignSelf": "full",
                    "borderRadius": 5,
                    "src": "https://yelp-photos-devc2.yelpcorp.com/bphoto/tLOYqTRzbjYMTTIw1VJosA/258s.jpg"
                  },
                  "type": "IMAGE"
                },
                {
                  "properties": {
                    "fontSize": 12,
                    "spacing": 0,
                    "text": {
                      "content": [
                        {
                          "marks": [
                            {
                              "type": "strong"
                            }
                          ],
                          "text": "Chicken Teriyaki",
                          "type": "text"
                        }
                      ],
                      "type": "doc"
                    }
                  },
                  "type": "TEXT"
                },
                {
                  "properties": {
                    "fontSize": 12,
                    "spacing": 0,
                    "text": {
                      "content": [
                        {
                          "text": "19 reviews • 7 photos",
                          "type": "text"
                        }
                      ],
                      "type": "paragraph"
                    }
                  },
                  "type": "TEXT"
                }
              ],
              "properties": {
                "spacing": 0.5
              },
              "type": "STACK_LAYOUT"
            }
          ],
          "properties": {
            "spacing": 0.85
          },
          "type": "CLUSTER_LAYOUT"
        }
      ],
      "properties": {
        "span": 3
      },
      "type": "COLUMN"
    }
  ],
  "type": "ROW"
}

